pylazy/__init__.py
pylazy/lazy.py
lazymethod-0.0.4.dist-info/WHEEL
lazymethod-0.0.4.dist-info/METADATA
lazymethod-0.0.4.dist-info/license_files/LICENSE
lazymethod-0.0.4.dist-info/RECORD
