Metadata-Version: 2.1
Name: lazymethod
Version: 0.0.4
Summary: pylazy 是一个 python 对象的懒加载装饰器，类似于 `@property` 但只会调用一次。
License: MIT
Author-email: baa-god <780810441@qq.com>
Requires-Python: >=3.8
